README.md
setup.py
end_to_end_tests/__init__.py
end_to_end_tests/basic_test.py
end_to_end_tests/interface.py
end_to_end_tests/manager.py
end_to_end_tests/timesketch.py
picatrix/__init__.py
picatrix/dependencies.py
picatrix/notebook_init.py
picatrix/version.py
picatrix.egg-info/PKG-INFO
picatrix.egg-info/SOURCES.txt
picatrix.egg-info/dependency_links.txt
picatrix.egg-info/not-zip-safe
picatrix.egg-info/requires.txt
picatrix.egg-info/top_level.txt
picatrix/helpers/__init__.py
picatrix/helpers/table.py
picatrix/lib/__init__.py
picatrix/lib/error.py
picatrix/lib/framework.py
picatrix/lib/framework_test.py
picatrix/lib/manager.py
picatrix/lib/manager_test.py
picatrix/lib/state.py
picatrix/lib/state_test.py
picatrix/lib/testlib.py
picatrix/lib/utils.py
picatrix/lib/utils_test.py
picatrix/magics/__init__.py
picatrix/magics/common.py
picatrix/magics/common_test.py
picatrix/magics/timesketch.py
picatrix/magics/timesketch_test.py