Metadata-Version: 1.2
Name: picatrix
Version: 20210519
Summary: Picatrix IPython Helpers
Home-page: https://github.com/google/picatrix/
Maintainer: Picatrix development team
Maintainer-email: picatrix-developers@googlegroups.com
License: Apache License, Version 2.0
Platform: UNKNOWN
Classifier: Development Status :: 4 - Beta
Classifier: Environment :: Console
Classifier: Operating System :: OS Independent
Classifier: Programming Language :: Python
